ScikitLearn019ZhongwenWendang/README.md
ScikitLearn019ZhongwenWendang/__init__.py
ScikitLearn019ZhongwenWendang/__main__.py
ScikitLearn019ZhongwenWendang/file.epub
ScikitLearn019ZhongwenWendang/index.html
ScikitLearn019ZhongwenWendang/css/__init__.py
ScikitLearn019ZhongwenWendang/css/annotations.css
ScikitLearn019ZhongwenWendang/css/main.css
ScikitLearn019ZhongwenWendang/css/normalize.css
ScikitLearn019ZhongwenWendang/css/popup.css
ScikitLearn019ZhongwenWendang/font/__init__.py
ScikitLearn019ZhongwenWendang/font/fontello.eot
ScikitLearn019ZhongwenWendang/font/fontello.svg
ScikitLearn019ZhongwenWendang/font/fontello.ttf
ScikitLearn019ZhongwenWendang/font/fontello.woff
ScikitLearn019ZhongwenWendang/img/__init__.py
ScikitLearn019ZhongwenWendang/img/annotator-glyph-sprite.png
ScikitLearn019ZhongwenWendang/img/annotator-icon-sprite.png
ScikitLearn019ZhongwenWendang/img/apple-touch-icon.png
ScikitLearn019ZhongwenWendang/img/cancelfullscreen.png
ScikitLearn019ZhongwenWendang/img/close.png
ScikitLearn019ZhongwenWendang/img/fullscreen.png
ScikitLearn019ZhongwenWendang/img/loader.gif
ScikitLearn019ZhongwenWendang/img/menu-icon.png
ScikitLearn019ZhongwenWendang/img/save.png
ScikitLearn019ZhongwenWendang/img/saved.png
ScikitLearn019ZhongwenWendang/img/settings-s.png
ScikitLearn019ZhongwenWendang/img/settings.png
ScikitLearn019ZhongwenWendang/img/star.png
ScikitLearn019ZhongwenWendang/js/__init__.py
ScikitLearn019ZhongwenWendang/js/epub.js
ScikitLearn019ZhongwenWendang/js/epub.min.js
ScikitLearn019ZhongwenWendang/js/epub.min.map
ScikitLearn019ZhongwenWendang/js/hooks.min.js
ScikitLearn019ZhongwenWendang/js/hooks.min.map
ScikitLearn019ZhongwenWendang/js/reader.js
ScikitLearn019ZhongwenWendang/js/reader.js.map
ScikitLearn019ZhongwenWendang/js/reader.min.js
ScikitLearn019ZhongwenWendang/js/reader.min.map
ScikitLearn019ZhongwenWendang/js/hooks/__init__.py
ScikitLearn019ZhongwenWendang/js/hooks/extensions/__init__.py
ScikitLearn019ZhongwenWendang/js/hooks/extensions/highlight.js
scikit_learn_0_19_zhongwen_wendang-2024.3.3.0.dist-info/METADATA
scikit_learn_0_19_zhongwen_wendang-2024.3.3.0.dist-info/WHEEL
scikit_learn_0_19_zhongwen_wendang-2024.3.3.0.dist-info/entry_points.txt
scikit_learn_0_19_zhongwen_wendang-2024.3.3.0.dist-info/top_level.txt
scikit_learn_0_19_zhongwen_wendang-2024.3.3.0.dist-info/RECORD
